cpl_media/__init__.py
cpl_media/common.py
cpl_media/player.py
cpl_media/recorder.kv
cpl_media/recorder.py
cpl_media/ffmpeg/__init__.py
cpl_media/ffmpeg/ffmpeg_player.kv
cpl_media/remote/__init__.py
cpl_media/remote/client.py
cpl_media/remote/client_player.kv
cpl_media/remote/server.py
cpl_media/remote/server_recorder.kv
cpl_media/rotpy/__init__.py
cpl_media/rotpy/rotpy_player.kv
cpl_media/rtv/__init__.py
cpl_media/rtv/rtv_player.kv
cpl_media/tests/__init__.py
cpl_media/tests/conftest.py
cpl_media/tests/media_test_app.py
cpl_media/tests/app/__init__.py
cpl_media/tests/app/demo_app.kv
cpl_media/tests/app/demo_app.py
cpl_media/tests/app/run_app.py
cpl_media/tests/app/test_play_file.py
cpl_media/thorcam/__init__.py
cpl_media/thorcam/thorcam_player.kv
cpl_media-0.1.4.dist-info/LICENSE
cpl_media-0.1.4.dist-info/METADATA
cpl_media-0.1.4.dist-info/WHEEL
cpl_media-0.1.4.dist-info/entry_points.txt
cpl_media-0.1.4.dist-info/top_level.txt
cpl_media-0.1.4.dist-info/RECORD
