Metadata-Version: 2.1
Name: cpl-media
Version: 0.1.4
Summary: Kivy support for playing and recording various cameras.
Home-page: https://github.com/matham/cpl_media
Author: Matthew Einhorn
Author-email: moiein2000@gmail.com
License: MIT
Project-URL: Bug Reports, https://github.com/matham/cpl_media/issues
Project-URL: Source, https://github.com/matham/cpl_media
Classifier: Development Status :: 4 - Beta
Classifier: Intended Audience :: Developers
Classifier: Topic :: Software Development :: Libraries
Classifier: License :: OSI Approved :: MIT License
Classifier: Programming Language :: Python :: 3.6
Classifier: Programming Language :: Python :: 3.7
Classifier: Programming Language :: Python :: 3.8
License-File: LICENSE
Requires-Dist: base-kivy-app (~=0.1.1)
Requires-Dist: ffpyplayer
Requires-Dist: kivy
Requires-Dist: tree-config
Provides-Extra: dev
Requires-Dist: pytest (>=3.6) ; extra == 'dev'
Requires-Dist: pytest-cov ; extra == 'dev'
Requires-Dist: flake8 ; extra == 'dev'
Requires-Dist: sphinx-rtd-theme ; extra == 'dev'
Requires-Dist: coveralls ; extra == 'dev'
Requires-Dist: trio ; extra == 'dev'
Requires-Dist: pytest-trio ; extra == 'dev'
